connectifycli/__init__.py
connectifycli/cli.py
connectifycli/graph/__init__.py
connectifycli/graph/graph.py
connectifycli/graph/model_info.py
connectifycli/utils/__init__.py
connectifycli/utils/json.py
connectifyai-0.1.1.dist-info/LICENSE.md
connectifyai-0.1.1.dist-info/METADATA
connectifyai-0.1.1.dist-info/WHEEL
connectifyai-0.1.1.dist-info/entry_points.txt
connectifyai-0.1.1.dist-info/top_level.txt
connectifyai-0.1.1.dist-info/RECORD
