Metadata-Version: 2.1
Name: connectifyai
Version: 0.1.1
Summary: A CLI to run ConnectifyAI graphs
Home-page: https://connectify-ai.vercel.app
Author: ConnectifyAI
Author-email: connectifyai2@gmail.com
Classifier: Topic :: Scientific/Engineering :: Artificial Intelligence
Classifier: Intended Audience :: Science/Research
Classifier: License :: OSI Approved :: GNU General Public License (GPL)
Classifier: Programming Language :: Python :: 3.8
Classifier: Programming Language :: Python :: 3.9
Classifier: Programming Language :: Python :: 3.10
Classifier: Programming Language :: Python :: 3.11
Classifier: Programming Language :: Python :: 3.12
Classifier: Programming Language :: Python :: 3.13
Classifier: Programming Language :: Python :: 3 :: Only
Requires-Python: >=3.8
License-File: LICENSE.md
Requires-Dist: Click
Requires-Dist: orjson
Requires-Dist: transformers
Requires-Dist: datasets
Requires-Dist: requests
